rally_token_auth/__init__.py
rally_token_auth/token_auth.py
sdvi_rally_token_auth-0.1.0.dist-info/LICENSE
sdvi_rally_token_auth-0.1.0.dist-info/METADATA
sdvi_rally_token_auth-0.1.0.dist-info/WHEEL
sdvi_rally_token_auth-0.1.0.dist-info/top_level.txt
sdvi_rally_token_auth-0.1.0.dist-info/RECORD
