Metadata-Version: 2.1
Name: sdvi-rally-token-auth
Version: 0.1.0
Summary: The Rally Token Auth Library
Home-page: UNKNOWN
Author: SDVI Corp
License: Proprietary
Platform: UNKNOWN
Classifier: Programming Language :: Python :: 3.6
Classifier: License :: Other/Proprietary License
Classifier: Operating System :: OS Independent
Requires-Python: >=3.6
License-File: LICENSE
Requires-Dist: requests
